bootstrapper.py
bootstrapper-1.1.0.dist-info/METADATA
bootstrapper-1.1.0.dist-info/RECORD
bootstrapper-1.1.0.dist-info/WHEEL
bootstrapper-1.1.0.dist-info/entry_points.txt
bootstrapper-1.1.0.dist-info/top_level.txt
