Metadata-Version: 2.1
Name: bootstrapper
Version: 1.1.0
Summary: Bootstrap Python projects with virtualenv and pip.
Home-page: https://github.com/playpauseandstop/bootstrapper
Author: Igor Davydenko
Author-email: playpauseandstop@gmail.com
License: BSD License
Keywords: bootstrap pip virtualenv
Platform: any
Classifier: Development Status :: 5 - Production/Stable
Classifier: Intended Audience :: Developers
Classifier: Intended Audience :: System Administrators
Classifier: License :: OSI Approved :: BSD License
Classifier: Operating System :: OS Independent
Classifier: Programming Language :: Python :: 2
Classifier: Programming Language :: Python :: 2.7
Classifier: Programming Language :: Python :: 3
Classifier: Programming Language :: Python :: 3.4
Classifier: Programming Language :: Python :: 3.5
Classifier: Programming Language :: Python :: 3.6
Classifier: Programming Language :: Python :: Implementation :: PyPy
Classifier: Topic :: System :: Systems Administration
Requires-Dist: virtualenv (>=1.10)
